LICENSE
README.md
setup.cfg
setup.py
precept/__init__.py
precept/_cli.py
precept/_configs.py
precept/_executor.py
precept/_immutable.py
precept/_logger.py
precept/_plugins.py
precept/_precept.py
precept/_services.py
precept/_tools.py
precept/_version.py
precept/errors.py
precept.egg-info/PKG-INFO
precept.egg-info/SOURCES.txt
precept.egg-info/dependency_links.txt
precept.egg-info/requires.txt
precept.egg-info/top_level.txt
precept/console/__init__.py
precept/console/_keyhandler.py
precept/console/_printing.py
precept/events/__init__.py
precept/events/_dispatcher.py
precept/events/_event.py