Metadata-Version: 2.1
Name: precept
Version: 0.6.5
Summary: Async cli application builder.
Home-page: https://github.com/T4rk1n/precept
Author: Philippe Duval
Author-email: t4rk@outlook.com
License: MIT
Keywords: cli,async
Platform: UNKNOWN
Classifier: Programming Language :: Python
Classifier: Programming Language :: Python :: 3.6
Classifier: Programming Language :: Python :: 3.7
Classifier: License :: OSI Approved :: MIT License
Classifier: Intended Audience :: Developers
License-File: LICENSE
